{
"texture":"flystar.png",
"blendFactorSource":"one"
,"maxRadiusVariance":30
,"lifespan":1500
,"blendFactorDestination":"oneMinusSourceAlpha"
,"minRadius":20
,"lifespanVariance":300
,"minRadiusVariance":10
,"startSize":60.86
,"rotatePerSecond":30
,"endRedVariance":0
,"tangentialAccelerationVariance":147.58
,"rotatePerSecondVariance":10
,"endSize":5
,"startAlphaVariance":0
,"emitterType":0
,"endAlphaVariance":0
,"endRed":255
,"emitAngle":225
,"startAlpha":0.023529411764705882
,"emitAngleVariance":360
,"startBlue":255
,"startBlueVariance":0
,"startRotation":-30
,"emitterVariance":{"x":7,"y":4}
,"startSizeVariance":12.88
,"startRotationVariance":0
,"endBlueVariance":0
,"endSizeVariance":5
,"endRotationVariance":0
,"startRedVariance":0
,"startGreenVariance":0
,"endRotation":-30
,"speedVariance":20
,"maxParticles":200
,"endAlpha":1
,"startRed":255
,"emitter":{"x":0,"y":0}
,"speed":72.65
,"radialAcceleration":16.65
,"endBlue":255
,"radialAccelerationVariance":0
,"duration":-1
,"endGreen":255
,"tangentialAcceleration":0
,"startGreen":255
,"gravity":{"x":0,"y":604.03}
,"engGreenVariance":0
,"maxRadius":100
}