{
	"groups": [
		{
			"keys": "Package1@atlas_sp8ru_jpg,Package1@atlas0_png,Package1,Package1@atlas_12czcy_jpg,Package1@atlas_12czcz_jpg,Package1@atlas_12czcx_jpg",
			"name": "preload"
		}
	],
	"resources": [
		{
			"name": "Package1@atlas_sp8ru_jpg",
			"type": "image",
			"url": "assets/Package1@atlas_sp8ru.jpg"
		},
		{
			"name": "Package1@atlas0_png",
			"type": "image",
			"url": "assets/Package1@atlas0.png"
		},
		{
			"name": "Package1",
			"type": "bin",
			"url": "assets/Package1.fui"
		},
		{
			"name": "Package1@atlas_12czcy_jpg",
			"type": "image",
			"url": "assets/Package1@atlas_12czcy.jpg"
		},
		{
			"name": "Package1@atlas_12czcz_jpg",
			"type": "image",
			"url": "assets/Package1@atlas_12czcz.jpg"
		},
		{
			"name": "Package1@atlas_12czcx_jpg",
			"type": "image",
			"url": "assets/Package1@atlas_12czcx.jpg"
		}
	]
}